CHANGELOG.txt
MANIFEST.in
README.rst
setup.cfg
setup.py
ucscgenome/__init__.py
ucscgenome/genome.py
ucscgenome.egg-info/PKG-INFO
ucscgenome.egg-info/SOURCES.txt
ucscgenome.egg-info/dependency_links.txt
ucscgenome.egg-info/requires.txt
ucscgenome.egg-info/top_level.txt
ucscgenome.egg-info/zip-safe