Metadata-Version: 1.1
Name: ucscgenome
Version: 0.1
Summary: Simple access to the reference genomes at UCSC
Home-page: https://github.com/konstantint/ucscgenome
Author: Konstantin Tretyakov
Author-email: kt@ut.ee
License: MIT
Keywords: bioinformatics ucsc data-access genome-analysis
Platform: Platform Independent
Classifier: Development Status :: 3 - Alpha
Classifier: Intended Audience :: Science/Research
Classifier: License :: OSI Approved :: MIT License
Classifier: Operating System :: OS Independent
Classifier: Programming Language :: Python :: 2
Classifier: Topic :: Scientific/Engineering :: Bio-Informatics
